pysentimiento/__init__.py
pysentimiento/analyzer.py
pysentimiento/baselines/__init__.py
pysentimiento/baselines/models.py
pysentimiento/baselines/training.py
pysentimiento/baselines/utils.py
pysentimiento/config.py
pysentimiento/emotion.py
pysentimiento/hate.py
pysentimiento/irony.py
pysentimiento/lince/__init__.py
pysentimiento/lince/ner.py
pysentimiento/lince/pos.py
pysentimiento/lince/sentiment.py
pysentimiento/metrics.py
pysentimiento/preprocessing.py
pysentimiento/semeval.py
pysentimiento/sentiment.py
pysentimiento/sentiment_pt.py
pysentimiento/sentipolc.py
pysentimiento/targeted_sa.py
pysentimiento/tass.py
pysentimiento/training.py
pysentimiento/tuning.py
pysentimiento/utils.py
pysentimiento-0.7.1.dist-info/WHEEL
pysentimiento-0.7.1.dist-info/METADATA
pysentimiento-0.7.1.dist-info/LICENSE.md
pysentimiento-0.7.1.dist-info/RECORD
