Metadata-Version: 2.1
Name: pysentimiento
Version: 0.7.1
Summary: A Transformer-based library for SocialNLP tasks
Home-page: https://github.com/pysentimiento/pysentimiento/
Author: Juan Manuel Pérez
Author-email: jmperez@dc.uba.ar
Requires-Python: >=3.8,<4.0
Classifier: Programming Language :: Python :: 3
Classifier: Programming Language :: Python :: 3.8
Classifier: Programming Language :: Python :: 3.9
Classifier: Programming Language :: Python :: 3.10
Classifier: Programming Language :: Python :: 3.11
Requires-Dist: datasets (>=1.13.3)
Requires-Dist: emoji (>=1.6.1,<2.0.0)
Requires-Dist: spacy (>=3.5.0,<4.0.0)
Requires-Dist: torch (>=2.0.0)
Requires-Dist: transformers (>=4.13.0)
Project-URL: Repository, https://github.com/pysentimiento/pysentimiento/
